kosis/__init__.py
kosis/kosis.py
kosis-0.1.5.dist-info/LICENSE
kosis-0.1.5.dist-info/METADATA
kosis-0.1.5.dist-info/WHEEL
kosis-0.1.5.dist-info/top_level.txt
kosis-0.1.5.dist-info/RECORD
