Metadata-Version: 2.1
Name: kosis
Version: 0.1.5
Summary: KOSIS API
Author-email: Euntaik Lee <euntaik@gmail.com>
Project-URL: Homepage, https://github.com/euntaik/kosis
Project-URL: Bug Tracker, https://github.com/euntaik/kosis/issues
Classifier: Programming Language :: Python :: 3
Classifier: License :: OSI Approved :: MIT License
Classifier: Operating System :: OS Independent
Requires-Python: >=3.7
License-File: LICENSE
Requires-Dist: pandas
Requires-Dist: plotly
Requires-Dist: requests
